<?xml version="1.0" encoding="utf-8" ?>
<defect_record version="1.1">
<index>1036</index>
<model>IphoneX SpaceGray</model>
<time>2019/06/20 13:22:22</time>
<station name="BACK">
<surface name="B">
<sensor name="smooth_surface_sensor_1" type="smooth_surface_sensor">
<parameter>
<defect_item index="1">
<enabled>1</enabled>
<color>0</color>
<threshold>20</threshold>
<defect_finder>
<sort><type>2</type>
<general><enabled>1</enabled>
<sort>2</sort>
</general>
<scratch><enabled>1</enabled>
<sort>1</sort>
<aspect_ratio>5</aspect_ratio>
</scratch><crack><enabled>0</enabled>
<sort>3</sort>
<aspect_ratio>10</aspect_ratio>
<max_gap>40</max_gap>
</crack></sort><defect_unit>0</defect_unit>
<defect>
<item>
<length_defect>
<min_length>0.1</min_length>
<max_length>1</max_length>
<min_width>0.1</min_width>
<min_count>1</min_count>
</length_defect>
</item>
</defect>
<scratch_linking>
<enabled>1</enabled>
<major_offset>1</major_offset>
<minor_offset>0.1</minor_offset>
<angle>30</angle>
</scratch_linking>
<cluster>
<enabled>1</enabled>
<range>3</range>
<min_length>0</min_length>
<max_length>1</max_length>
<min_width>0</min_width>
<max_width>0.5</max_width>
<min_count>3</min_count>
</cluster>
</defect_finder>
</defect_item>
<defect_item index="2">
<enabled>1</enabled>
<color>0</color>
<threshold>15</threshold>
<defect_finder>
<sort><type>-1</type>
<general><enabled>1</enabled>
<sort>2</sort>
</general>
<scratch><enabled>1</enabled>
<sort>1</sort>
<aspect_ratio>5</aspect_ratio>
</scratch><crack><enabled>0</enabled>
<sort>3</sort>
<aspect_ratio>3</aspect_ratio>
<max_gap>40</max_gap>
</crack></sort><defect_unit>0</defect_unit>
<defect>
<item>
<length_defect>
<min_length>1</min_length>
<min_width>0</min_width>
<min_count>1</min_count>
</length_defect>
</item>
</defect>
<scratch_linking>
<enabled>1</enabled>
<major_offset>1</major_offset>
<minor_offset>0.1</minor_offset>
<angle>30</angle>
</scratch_linking>
<cluster>
<enabled>0</enabled>
<range>2</range>
<min_length>0</min_length>
<max_length>1</max_length>
<min_width>0</min_width>
<max_width>0.2</max_width>
<min_count>3</min_count>
</cluster>
</defect_finder>
</defect_item>
</parameter>
<region>512,951,11179,6520</region>
<defect>
<item class="defect">
<type>PinDotGroup</type>
<defect_item>1</defect_item>
<length>3.41744</length>
<width>0.497811</width>
<area_mm>0.173573</area_mm>
<area_pixel>894</area_pixel>
<contrast>42</contrast>
<location>
<point>3431.49,1880.45</point>
<point>3642.52,2005.43</point>
<point>3660.72,1974.69</point>
<point>3449.7,1849.71</point>
</location>
</item>
<item class="defect">
<type>PinDotGroup</type>
<defect_item>1</defect_item>
<length>4.83546</length>
<width>3.01051</width>
<area_mm>0.398597</area_mm>
<area_pixel>2053</area_pixel>
<contrast>62</contrast>
<location>
<point>4433.41,5916.57</point>
<point>4756.99,5791.17</point>
<point>4678.92,5589.71</point>
<point>4355.34,5715.11</point>
</location>
</item>
<item class="defect">
<type>Scratch</type>
<defect_item>2</defect_item>
<length>2.09825</length>
<width>0.0667888</width>
<area_mm>0.170855</area_mm>
<area_pixel>880</area_pixel>
<contrast>68</contrast>
<location>
<point>9075.45,1817.97</point>
<point>9150.03,1687.15</point>
<point>9135.97,1679.13</point>
<point>9061.39,1809.95</point>
</location>
</item>
<item class="defect">
<type>Scratch</type>
<defect_item>2</defect_item>
<length>1.93444</length>
<width>0.0504242</width>
<area_mm>0.122317</area_mm>
<area_pixel>630</area_pixel>
<contrast>31</contrast>
<location>
<point>9028.67,1825.48</point>
<point>9095.06,1703.55</point>
<point>9083.01,1696.99</point>
<point>9016.63,1818.92</point>
</location>
</item>
<item class="defect">
<type>Scratch</type>
<defect_item>2</defect_item>
<length>1.26713</length>
<width>0.164338</width>
<area_mm>0.196678</area_mm>
<area_pixel>1013</area_pixel>
<contrast>36</contrast>
<location>
<point>3587.68,1990.82</point>
<point>3678.6,1988.93</point>
<point>3677.89,1954.52</point>
<point>3586.97,1956.42</point>
</location>
</item>
<item class="defect">
<type>Scratch</type>
<defect_item>2</defect_item>
<length>1.47267</length>
<width>0.10232</width>
<area_mm>0.167943</area_mm>
<area_pixel>865</area_pixel>
<contrast>62</contrast>
<location>
<point>7816.99,2020.23</point>
<point>7921.97,2008.02</point>
<point>7920.21,1992.89</point>
<point>7815.23,2005.1</point>
</location>
</item>
<item class="defect">
<type>Scratch</type>
<defect_item>2</defect_item>
<length>1.07859</length>
<width>0.193636</width>
<area_mm>0.207744</area_mm>
<area_pixel>1070</area_pixel>
<contrast>56</contrast>
<location>
<point>3396.86,2229.19</point>
<point>3464.05,2267.64</point>
<point>3482.47,2235.45</point>
<point>3415.28,2197.01</point>
</location>
</item>
<item class="defect">
<type>Scratch</type>
<defect_item>2</defect_item>
<length>1.26294</length>
<width>0.192141</width>
<area_mm>0.237062</area_mm>
<area_pixel>1221</area_pixel>
<contrast>46</contrast>
<location>
<point>4454.76,4313.11</point>
<point>4545.31,4317.25</point>
<point>4546.49,4291.44</point>
<point>4455.94,4287.3</point>
</location>
</item>
<item class="defect">
<type>Scratch</type>
<defect_item>2</defect_item>
<length>2.34095</length>
<width>0.120065</width>
<area_mm>0.289483</area_mm>
<area_pixel>1491</area_pixel>
<contrast>37</contrast>
<location>
<point>1895.49,5110.49</point>
<point>2063.5,5110.74</point>
<point>2063.53,5089.62</point>
<point>1895.53,5089.37</point>
</location>
</item>
<item class="defect">
<type>Nick</type>
<defect_item>2</defect_item>
<length>1.06382</length>
<width>0.267445</width>
<area_mm>0.290065</area_mm>
<area_pixel>1494</area_pixel>
<contrast>80</contrast>
<location>
<point>3479.72,1882.97</point>
<point>3555.67,1875.18</point>
<point>3552.32,1842.44</point>
<point>3476.37,1850.22</point>
</location>
</item>
<item class="defect">
<type>Nick</type>
<defect_item>2</defect_item>
<length>1.67338</length>
<width>0.430766</width>
<area_mm>0.723416</area_mm>
<area_pixel>3726</area_pixel>
<contrast>77</contrast>
<location>
<point>2731.73,1933.18</point>
<point>2851.64,1926.52</point>
<point>2848.9,1877.28</point>
<point>2728.99,1883.95</point>
</location>
</item>
<item class="defect">
<type>Nick</type>
<defect_item>2</defect_item>
<length>1.10427</length>
<width>0.252226</width>
<area_mm>0.278028</area_mm>
<area_pixel>1432</area_pixel>
<contrast>58</contrast>
<location>
<point>3260.06,2253.83</point>
<point>3339.17,2249.04</point>
<point>3337.05,2214.13</point>
<point>3257.95,2218.93</point>
</location>
</item>
<item class="defect">
<type>Nick</type>
<defect_item>2</defect_item>
<length>1.15946</length>
<width>0.300318</width>
<area_mm>0.322877</area_mm>
<area_pixel>1663</area_pixel>
<contrast>52</contrast>
<location>
<point>3549.35,2427.86</point>
<point>3632.25,2420.66</point>
<point>3627.91,2370.73</point>
<point>3545.02,2377.93</point>
</location>
</item>
<item class="defect">
<type>Nick</type>
<defect_item>2</defect_item>
<length>1.15733</length>
<width>0.307766</width>
<area_mm>0.34074</area_mm>
<area_pixel>1755</area_pixel>
<contrast>43</contrast>
<location>
<point>3870.27,3375.79</point>
<point>3953.13,3381.59</point>
<point>3956.42,3334.54</point>
<point>3873.57,3328.74</point>
</location>
</item>
<item class="defect">
<type>Nick</type>
<defect_item>2</defect_item>
<length>2.08951</length>
<width>0.747989</width>
<area_mm>1.37247</area_mm>
<area_pixel>7069</area_pixel>
<contrast>73</contrast>
<location>
<point>4848.72,6094.34</point>
<point>4998.45,6102.51</point>
<point>5002.81,6022.62</point>
<point>4853.08,6014.44</point>
</location>
</item>
</defect>
</sensor>
</surface>
</station>
<station name="DOWN">
<surface name="B">
<sensor name="edge_sensor_1" type="edge_sensor">
<parameter>
<defect_item index="1">
<enabled>1</enabled>
<threshold>15</threshold>
<defect_finder>
<sort><type>-1</type>
<general><enabled>1</enabled>
<sort>2</sort>
</general>
<scratch><enabled>1</enabled>
<sort>1</sort>
<aspect_ratio>5</aspect_ratio>
</scratch><crack><enabled>0</enabled>
<sort>3</sort>
<aspect_ratio>10</aspect_ratio>
<max_gap>40</max_gap>
</crack></sort><defect_unit>0</defect_unit>
<defect>
<item>
<length_defect>
<min_length>0.5</min_length>
<min_width>0.1</min_width>
<min_count>1</min_count>
</length_defect>
</item>
</defect>
<scratch_linking>
<enabled>1</enabled>
<major_offset>1</major_offset>
<minor_offset>0.1</minor_offset>
<angle>30</angle>
</scratch_linking>
<cluster>
<enabled>1</enabled>
<range>2</range>
<min_length>0</min_length>
<max_length>1</max_length>
<min_width>0</min_width>
<max_width>0.5</max_width>
<min_count>3</min_count>
</cluster>
</defect_finder>
</defect_item>
</parameter>
<region>354,580,1590,683</region>
<defect>
<item class="defect">
<type>Scratch</type>
<defect_item>1</defect_item>
<length>7.72005</length>
<width>0.303701</width>
<area_mm>2.35008</area_mm>
<area_pixel>1022</area_pixel>
<contrast>62</contrast>
<location>
<point>892.527,681.802</point>
<point>1053.52,681.395</point>
<point>1053.49,670.095</point>
<point>892.499,670.501</point>
</location>
</item>
<item class="defect">
<type>Nick</type>
<defect_item>1</defect_item>
<length>1.76593</length>
<width>0.384955</width>
<area_mm>0.703644</area_mm>
<area_pixel>306</area_pixel>
<contrast>58</contrast>
<location>
<point>1187.3,640.017</point>
<point>1204.7,607.56</point>
<point>1189.08,599.189</point>
<point>1171.68,631.646</point>
</location>
</item>
<item class="defect">
<type>PinDotGroup</type>
<defect_item>1</defect_item>
<length>3.39233</length>
<width>1.06746</width>
<area_mm>0.581771</area_mm>
<area_pixel>253</area_pixel>
<contrast>63</contrast>
<location>
<point>748.534,617.106</point>
<point>802.239,663.152</point>
<point>816.729,646.253</point>
<point>763.023,600.207</point>
</location>
</item>
</defect>
</sensor>
</surface>
</station>
<station name="UP">
<surface name="B">
<sensor name="edge_sensor_1" type="edge_sensor">
<parameter>
<defect_item index="1">
<enabled>1</enabled>
<threshold>15</threshold>
<defect_finder>
<sort><type>-1</type>
<general><enabled>1</enabled>
<sort>2</sort>
</general>
<scratch><enabled>1</enabled>
<sort>1</sort>
<aspect_ratio>5</aspect_ratio>
</scratch><crack><enabled>0</enabled>
<sort>3</sort>
<aspect_ratio>10</aspect_ratio>
<max_gap>40</max_gap>
</crack></sort><defect_unit>0</defect_unit>
<defect>
<item>
<length_defect>
<min_length>0.4</min_length>
<min_width>0.2</min_width>
<min_count>1</min_count>
</length_defect>
</item>
</defect>
<scratch_linking>
<enabled>1</enabled>
<major_offset>1</major_offset>
<minor_offset>0.1</minor_offset>
<angle>30</angle>
</scratch_linking>
<cluster>
<enabled>1</enabled>
<range>2</range>
<min_length>0</min_length>
<max_length>1</max_length>
<min_width>0</min_width>
<max_width>0.2</max_width>
<min_count>3</min_count>
</cluster>
</defect_finder>
</defect_item>
</parameter>
<region>379,586,1613,688</region>
<defect>
<item class="defect">
<type>Nick</type>
<defect_item>1</defect_item>
<length>0.622391</length>
<width>0.225039</width>
<area_mm>0.147167</area_mm>
<area_pixel>64</area_pixel>
<contrast>38</contrast>
<location>
<point>692.195,649.842</point>
<point>692.959,662.798</point>
<point>701.109,662.317</point>
<point>700.345,649.361</point>
</location>
</item>
<item class="defect">
<type>Nick</type>
<defect_item>1</defect_item>
<length>0.537285</length>
<width>0.23722</width>
<area_mm>0.140269</area_mm>
<area_pixel>61</area_pixel>
<contrast>59</contrast>
<location>
<point>788.652,680.616</point>
<point>799.082,684.708</point>
<point>802.701,675.484</point>
<point>792.271,671.392</point>
</location>
</item>
</defect>
</sensor>
</surface>
</station>
<station name="LEFT">
<surface name="B">
<sensor name="edge_sensor_3" type="edge_sensor">
<parameter>
<defect_item index="1">
<enabled>1</enabled>
<threshold>20</threshold>
<defect_finder>
<sort><type>-1</type>
<general><enabled>1</enabled>
<sort>2</sort>
</general>
<scratch><enabled>1</enabled>
<sort>1</sort>
<aspect_ratio>5</aspect_ratio>
</scratch><crack><enabled>0</enabled>
<sort>3</sort>
<aspect_ratio>10</aspect_ratio>
<max_gap>40</max_gap>
</crack></sort><defect_unit>0</defect_unit>
<defect>
<item>
<length_defect>
<min_length>0.2</min_length>
<min_width>0.1</min_width>
<min_count>1</min_count>
</length_defect>
</item>
</defect>
<scratch_linking>
<enabled>1</enabled>
<major_offset>1</major_offset>
<minor_offset>0.1</minor_offset>
<angle>30</angle>
</scratch_linking>
<cluster>
<enabled>1</enabled>
<range>3</range>
<min_length>0</min_length>
<max_length>1</max_length>
<min_width>0</min_width>
<max_width>0.5</max_width>
<min_count>3</min_count>
</cluster>
</defect_finder>
</defect_item>
</parameter>
<region>2165,521,3532,619</region>
<defect>
<item class="defect">
<type>Nick</type>
<defect_item>1</defect_item>
<length>1.01173</length>
<width>0.450171</width>
<area_mm>0.413556</area_mm>
<area_pixel>181</area_pixel>
<contrast>56</contrast>
<location>
<point>2490.19,573.394</point>
<point>2499.27,554.274</point>
<point>2482.64,546.377</point>
<point>2473.56,565.497</point>
</location>
</item>
<item class="defect">
<type>PinDotGroup</type>
<defect_item>1</defect_item>
<length>2.89208</length>
<width>0.893873</width>
<area_mm>0.125666</area_mm>
<area_pixel>55</area_pixel>
<contrast>48</contrast>
<location>
<point>2942.2,612.266</point>
<point>3001.7,601.27</point>
<point>2998.3,582.881</point>
<point>2938.81,593.877</point>
</location>
</item>
</defect>
</sensor>
<sensor name="edge_sensor_4" type="edge_sensor">
<parameter>
<defect_item index="1">
<enabled>1</enabled>
<threshold>15</threshold>
<defect_finder>
<sort><type>-1</type>
<general><enabled>1</enabled>
<sort>2</sort>
</general>
<scratch><enabled>1</enabled>
<sort>1</sort>
<aspect_ratio>5</aspect_ratio>
</scratch><crack><enabled>0</enabled>
<sort>3</sort>
<aspect_ratio>10</aspect_ratio>
<max_gap>40</max_gap>
</crack></sort><defect_unit>0</defect_unit>
<defect>
<item>
<length_defect>
<min_length>0.2</min_length>
<min_width>0.2</min_width>
<min_count>1</min_count>
</length_defect>
</item>
</defect>
<scratch_linking>
<enabled>1</enabled>
<major_offset>1</major_offset>
<minor_offset>0.1</minor_offset>
<angle>30</angle>
</scratch_linking>
<cluster>
<enabled>1</enabled>
<range>2</range>
<min_length>0</min_length>
<max_length>1</max_length>
<min_width>0</min_width>
<max_width>0.2</max_width>
<min_count>3</min_count>
</cluster>
</defect_finder>
</defect_item>
</parameter>
<region>1019,522,1213,621</region>
<defect>
<item class="defect">
<type>Nick</type>
<defect_item>1</defect_item>
<length>1.04156</length>
<width>0.356129</width>
<area_mm>0.301599</area_mm>
<area_pixel>132</area_pixel>
<contrast>38</contrast>
<location>
<point>1094.98,575.574</point>
<point>1106.78,593.892</point>
<point>1118.88,586.096</point>
<point>1107.08,567.779</point>
</location>
</item>
</defect>
</sensor>
</surface>
</station>
<station name="RIGHT">
<surface name="B">
<sensor name="edge_sensor_4" type="edge_sensor">
<parameter>
<defect_item index="1">
<enabled>1</enabled>
<threshold>15</threshold>
<defect_finder>
<sort><type>-1</type>
<general><enabled>1</enabled>
<sort>2</sort>
</general>
<scratch><enabled>1</enabled>
<sort>1</sort>
<aspect_ratio>5</aspect_ratio>
</scratch><crack><enabled>0</enabled>
<sort>3</sort>
<aspect_ratio>10</aspect_ratio>
<max_gap>40</max_gap>
</crack></sort><defect_unit>0</defect_unit>
<defect>
<item>
<length_defect>
<min_length>0.5</min_length>
<min_width>0.2</min_width>
<min_count>1</min_count>
</length_defect>
</item>
</defect>
<scratch_linking>
<enabled>1</enabled>
<major_offset>1</major_offset>
<minor_offset>0.1</minor_offset>
<angle>30</angle>
</scratch_linking>
<cluster>
<enabled>1</enabled>
<range>1</range>
<min_length>0</min_length>
<max_length>1</max_length>
<min_width>0</min_width>
<max_width>0.2</max_width>
<min_count>2</min_count>
</cluster>
</defect_finder>
</defect_item>
</parameter>
<region>6494,540,6681,638</region>
<defect>
<item class="defect">
<type>Nick</type>
<defect_item>1</defect_item>
<length>1.36468</length>
<width>0.33944</width>
<area_mm>0.386138</area_mm>
<area_pixel>169</area_pixel>
<contrast>45</contrast>
<location>
<point>6572.94,619.141</point>
<point>6593.64,599.48</point>
<point>6579.05,584.116</point>
<point>6558.35,603.777</point>
</location>
</item>
</defect>
</sensor>
<sensor name="edge_sensor_1" type="edge_sensor">
<parameter>
<defect_item index="1">
<enabled>1</enabled>
<threshold>15</threshold>
<defect_finder>
<sort><type>-1</type>
<general><enabled>1</enabled>
<sort>2</sort>
</general>
<scratch><enabled>1</enabled>
<sort>1</sort>
<aspect_ratio>5</aspect_ratio>
</scratch><crack><enabled>0</enabled>
<sort>3</sort>
<aspect_ratio>10</aspect_ratio>
<max_gap>40</max_gap>
</crack></sort><defect_unit>0</defect_unit>
<defect>
<item>
<length_defect>
<min_length>0.5</min_length>
<min_width>0.2</min_width>
<min_count>1</min_count>
</length_defect>
</item>
</defect>
<scratch_linking>
<enabled>1</enabled>
<major_offset>1</major_offset>
<minor_offset>0.1</minor_offset>
<angle>30</angle>
</scratch_linking>
<cluster>
<enabled>1</enabled>
<range>1</range>
<min_length>0</min_length>
<max_length>1</max_length>
<min_width>0</min_width>
<max_width>0.2</max_width>
<min_count>2</min_count>
</cluster>
</defect_finder>
</defect_item>
</parameter>
<region>1074,536,1267,631</region>
<defect>
<item class="defect">
<type>Nick</type>
<defect_item>1</defect_item>
<length>0.784452</length>
<width>0.350529</width>
<area_mm>0.233054</area_mm>
<area_pixel>102</area_pixel>
<contrast>47</contrast>
<location>
<point>1185.33,615.33</point>
<point>1198.41,625.245</point>
<point>1206.02,615.209</point>
<point>1192.94,605.295</point>
</location>
</item>
</defect>
</sensor>
<sensor name="edge_sensor_2" type="edge_sensor">
<parameter>
<defect_item index="1">
<enabled>1</enabled>
<threshold>20</threshold>
<defect_finder>
<sort><type>-1</type>
<general><enabled>1</enabled>
<sort>2</sort>
</general>
<scratch><enabled>1</enabled>
<sort>1</sort>
<aspect_ratio>5</aspect_ratio>
</scratch><crack><enabled>0</enabled>
<sort>3</sort>
<aspect_ratio>10</aspect_ratio>
<max_gap>40</max_gap>
</crack></sort><defect_unit>0</defect_unit>
<defect>
<item>
<length_defect>
<min_length>0.1</min_length>
<min_width>0.2</min_width>
<min_count>1</min_count>
</length_defect>
</item>
</defect>
<scratch_linking>
<enabled>1</enabled>
<major_offset>1</major_offset>
<minor_offset>0.1</minor_offset>
<angle>30</angle>
</scratch_linking>
<cluster>
<enabled>1</enabled>
<range>3</range>
<min_length>0</min_length>
<max_length>1</max_length>
<min_width>0</min_width>
<max_width>0.5</max_width>
<min_count>3</min_count>
</cluster>
</defect_finder>
</defect_item>
</parameter>
<region>2215,543,3788,637</region>
<defect>
<item class="defect">
<type>Nick</type>
<defect_item>1</defect_item>
<length>1.15834</length>
<width>0.619898</width>
<area_mm>0.614622</area_mm>
<area_pixel>269</area_pixel>
<contrast>55</contrast>
<location>
<point>3759.79,631.331</point>
<point>3780.26,618.361</point>
<point>3769.34,601.126</point>
<point>3748.87,614.097</point>
</location>
</item>
</defect>
</sensor>
</surface>
</station>
<station name="TOP">
<surface name="AA">
<sensor name="glass_sensor_1" type="glass_sensor">
<parameter>
<defect_item index="1">
<enabled>1</enabled>
<color>0</color>
<threshold>2</threshold>
<defect_finder>
<sort><type>-1</type>
<general><enabled>1</enabled>
<sort>2</sort>
</general>
<scratch><enabled>1</enabled>
<sort>1</sort>
<aspect_ratio>5</aspect_ratio>
</scratch><crack><enabled>0</enabled>
<sort>3</sort>
<aspect_ratio>10</aspect_ratio>
<max_gap>40</max_gap>
</crack></sort><defect_unit>0</defect_unit>
<defect>
<item>
<length_defect>
<min_length>1.5</min_length>
<min_width>0</min_width>
<max_width>0.17</max_width>
<min_count>1</min_count>
</length_defect>
</item>
</defect>
<scratch_linking>
<enabled>1</enabled>
<major_offset>2</major_offset>
<minor_offset>0.1</minor_offset>
<angle>30</angle>
</scratch_linking>
<cluster>
<enabled>0</enabled>
<range>1</range>
<min_length>0</min_length>
<max_length>1</max_length>
<min_width>0</min_width>
<max_width>0.2</max_width>
<min_count>2</min_count>
</cluster>
</defect_finder>
</defect_item>
<defect_item index="2">
<enabled>1</enabled>
<color>0</color>
<threshold>15</threshold>
<defect_finder>
<sort><type>-1</type>
<general><enabled>1</enabled>
<sort>2</sort>
</general>
<scratch><enabled>1</enabled>
<sort>1</sort>
<aspect_ratio>5</aspect_ratio>
</scratch><crack><enabled>0</enabled>
<sort>3</sort>
<aspect_ratio>10</aspect_ratio>
<max_gap>40</max_gap>
</crack></sort><defect_unit>0</defect_unit>
<defect>
<item>
<length_defect>
<min_length>0.5</min_length>
<min_width>0.1</min_width>
<min_count>1</min_count>
</length_defect>
</item>
</defect>
<scratch_linking>
<enabled>1</enabled>
<major_offset>2</major_offset>
<minor_offset>0.1</minor_offset>
<angle>30</angle>
</scratch_linking>
<cluster>
<enabled>0</enabled>
<range>1</range>
<min_length>0</min_length>
<max_length>1</max_length>
<min_width>0</min_width>
<max_width>0.2</max_width>
<min_count>2</min_count>
</cluster>
</defect_finder>
</defect_item>
<defect_item index="3">
<enabled>1</enabled>
<color>0</color>
<threshold>50</threshold>
<defect_finder>
<sort><type>-1</type>
<general><enabled>1</enabled>
<sort>2</sort>
</general>
<scratch><enabled>1</enabled>
<sort>1</sort>
<aspect_ratio>5</aspect_ratio>
</scratch><crack><enabled>0</enabled>
<sort>3</sort>
<aspect_ratio>10</aspect_ratio>
<max_gap>40</max_gap>
</crack></sort><defect_unit>0</defect_unit>
<defect>
<item>
<length_defect>
<min_length>0.5</min_length>
<min_width>0</min_width>
<min_count>1</min_count>
</length_defect>
</item>
</defect>
<scratch_linking>
<enabled>1</enabled>
<major_offset>1</major_offset>
<minor_offset>0.1</minor_offset>
<angle>30</angle>
</scratch_linking>
<cluster>
<enabled>1</enabled>
<range>1</range>
<min_length>0</min_length>
<max_length>1</max_length>
<min_width>0</min_width>
<max_width>0.2</max_width>
<min_count>2</min_count>
</cluster>
</defect_finder>
</defect_item>
</parameter>
<region>528,1130,10990,6257</region>
<defect>
<item class="defect">
<type>Scratch</type>
<defect_item>1</defect_item>
<length>7.64678</length>
<width>0.157283</width>
<area_mm>1.03445</area_mm>
<area_pixel>5328</area_pixel>
<contrast>5</contrast>
<location>
<point>1854.53,2880.28</point>
<point>2118.06,3361.65</point>
<point>2171.18,3332.57</point>
<point>1907.65,2851.2</point>
</location>
</item>
<item class="defect">
<type>Scratch</type>
<defect_item>1</defect_item>
<length>1.81601</length>
<width>0.0960617</width>
<area_mm>0.15707</area_mm>
<area_pixel>809</area_pixel>
<contrast>3</contrast>
<location>
<point>6152.99,3707.69</point>
<point>6202.42,3587.09</point>
<point>6182.28,3578.84</point>
<point>6132.85,3699.43</point>
</location>
</item>
<item class="defect">
<type>Scratch</type>
<defect_item>1</defect_item>
<length>3.33364</length>
<width>0.104772</width>
<area_mm>0.32909</area_mm>
<area_pixel>1695</area_pixel>
<contrast>4</contrast>
<location>
<point>6861.27,4504.03</point>
<point>6898.03,4740.43</point>
<point>6952.56,4731.95</point>
<point>6915.8,4495.55</point>
</location>
</item>
<item class="defect">
<type>Scratch</type>
<defect_item>1</defect_item>
<length>1.67903</length>
<width>0.111198</width>
<area_mm>0.176291</area_mm>
<area_pixel>908</area_pixel>
<contrast>4</contrast>
<location>
<point>5167.03,4624.29</point>
<point>5287.48,4627.57</point>
<point>5288.39,4594.09</point>
<point>5167.94,4590.81</point>
</location>
</item>
<item class="defect">
<type>Scratch</type>
<defect_item>1</defect_item>
<length>1.92255</length>
<width>0.124305</width>
<area_mm>0.215899</area_mm>
<area_pixel>1112</area_pixel>
<contrast>4</contrast>
<location>
<point>5274.54,4635.22</point>
<point>5285.1,4772.8</point>
<point>5317.07,4770.34</point>
<point>5306.5,4632.77</point>
</location>
</item>
<item class="defect">
<type>Scratch</type>
<defect_item>1</defect_item>
<length>2.97958</length>
<width>0.105417</width>
<area_mm>0.298608</area_mm>
<area_pixel>1538</area_pixel>
<contrast>3</contrast>
<location>
<point>2732.19,5292.64</point>
<point>2927.29,5380.17</point>
<point>2939.88,5352.11</point>
<point>2744.78,5264.58</point>
</location>
</item>
</defect>
</sensor>
</surface>
</station>
</defect_record>
