{
    "imei": "353336076538553",
    "model": "APL6SP",
    "color": "ROSE GOLD",
    "vzw": "A",
    "defects": [
        {
            "type": "Nick",
            "defect_item": 1,
            "length": 0.759478,
            "width": 0.234501,
            "area_mm": 0.149887,
            "area_pixel": 772,
            "contrast": 55,
            "location": [
                "11638.3,1876.18",
                "11685.1,1904.21",
                "11703.1,1874.09",
                "11656.4,1846.05"
            ],
            "class": "defect",
            "surface": "B"
        },
        {
            "type": "Nick",
            "defect_item": 1,
            "length": 0.648145,
            "width": 0.34841,
            "area_mm": 0.1926,
            "area_pixel": 992,
            "contrast": 42,
            "location": [
                "1415.08,3641.92",
                "1446.52,3607.64",
                "1418.7,3582.13",
                "1387.27,3616.42"
            ],
            "class": "defect",
            "surface": "B"
        },
        {
            "type": "Discoloration",
            "region": "Mic",
            "value": 9.7252,
            "class": "measurement",
            "surface": "B"
        },
        {
            "type": "Scratch",
            "defect_item": 1,
            "length": 3.08335,
            "width": 0.1144,
            "area_mm": 0.362873,
            "area_pixel": 1869,
            "contrast": 6,
            "location": [
                "2955.07,3895.71",
                "3018.18,3683.62",
                "2984.24,3673.51",
                "2921.12,3885.61"
            ],
            "class": "defect",
            "surface": "AA"
        },
        {
            "type": "Scratch",
            "defect_item": 1,
            "length": 25.2401,
            "width": 0.0931933,
            "area_mm": 2.19607,
            "area_pixel": 11311,
            "contrast": 5,
            "location": [
                "3646.28,4752.34",
                "4673.33,6244.46",
                "4761.42,6183.82",
                "3734.37,4691.71"
            ],
            "class": "defect",
            "surface": "AA"
        },
        {
            "type": "Scratch",
            "defect_item": 1,
            "length": 2.67562,
            "width": 0.0820137,
            "area_mm": 0.19163,
            "area_pixel": 987,
            "contrast": 3,
            "location": [
                "6211.52,6387.93",
                "6403.54,6386.65",
                "6403.41,6366.73",
                "6211.39,6368"
            ],
            "class": "defect",
            "surface": "AA"
        }
    ]
}