{
    "imei": "356118090167347",
    "model": "APL8P",
    "color": "RED",
    "vzw": "C",
    "defects": [
        {
            "type": "Scratch",
            "defect_item": 1,
            "length": 0.821648,
            "width": 0.161727,
            "area_mm": 0.120181,
            "area_pixel": 619,
            "contrast": 19,
            "location": [
                "1036.89,1703.3",
                "1078.2,1745.38",
                "1099.07,1724.89",
                "1057.75,1682.81"
            ],
            "class": "defect",
            "surface": "B"
        },
        {
            "type": "PinDotGroup",
            "defect_item": 1,
            "length": 3.44624,
            "width": 0.796846,
            "area_mm": 0.239197,
            "area_pixel": 1232,
            "contrast": 19,
            "location": [
                "9182.97,2585.09",
                "9294.67,2364.42",
                "9243.65,2338.59",
                "9131.95,2559.26"
            ],
            "class": "defect",
            "surface": "B"
        },
        {
            "type": "PinDotGroup",
            "defect_item": 1,
            "length": 3.07834,
            "width": 1.15891,
            "area_mm": 0.284047,
            "area_pixel": 1463,
            "contrast": 14,
            "location": [
                "11590.2,4172.62",
                "11657.9,4382.92",
                "11737.1,4357.44",
                "11669.4,4147.14"
            ],
            "class": "defect",
            "surface": "B"
        },
        {
            "type": "Scratch",
            "defect_item": 2,
            "length": 4.22198,
            "width": 0.015064,
            "area_mm": 0.0667888,
            "area_pixel": 344,
            "contrast": 17,
            "location": [
                "9874.85,2053.61",
                "9923.24,1754.5",
                "9915.34,1753.23",
                "9866.95,2052.34"
            ],
            "class": "defect",
            "surface": "B"
        },
        {
            "type": "Scratch",
            "defect_item": 2,
            "length": 10.033,
            "width": 0.219818,
            "area_mm": 0.539941,
            "area_pixel": 2781,
            "contrast": 19,
            "location": [
                "9291.29,1900.16",
                "9503.08,2588.35",
                "9568.61,2568.18",
                "9356.82,1879.99"
            ],
            "class": "defect",
            "surface": "B"
        },
        {
            "type": "Scratch",
            "defect_item": 2,
            "length": 6.96281,
            "width": 1.34783,
            "area_mm": 1.11308,
            "area_pixel": 5733,
            "contrast": 29,
            "location": [
                "9969.86,2716.6",
                "10192.2,2269.1",
                "9957.62,2152.52",
                "9735.25,2600.03"
            ],
            "class": "defect",
            "surface": "B"
        },
        {
            "type": "Scratch",
            "defect_item": 2,
            "length": 3.04141,
            "width": 0.0152601,
            "area_mm": 0.0710602,
            "area_pixel": 366,
            "contrast": 17,
            "location": [
                "11202.4,3042.79",
                "11350.8,3202.89",
                "11353.4,3200.5",
                "11205,3040.4"
            ],
            "class": "defect",
            "surface": "B"
        },
        {
            "type": "Scratch",
            "defect_item": 2,
            "length": 1.66996,
            "width": 0.0392672,
            "area_mm": 0.0825153,
            "area_pixel": 425,
            "contrast": 24,
            "location": [
                "9098.26,1333.2",
                "9128.37,1449.2",
                "9141.24,1445.86",
                "9111.13,1329.86"
            ],
            "class": "defect",
            "surface": "B"
        },
        {
            "type": "Scratch",
            "defect_item": 2,
            "length": 2.3052,
            "width": 0.024509,
            "area_mm": 0.0867866,
            "area_pixel": 447,
            "contrast": 20,
            "location": [
                "9362.38,1347.24",
                "9487,1456.05",
                "9490.43,1452.12",
                "9365.81,1343.31"
            ],
            "class": "defect",
            "surface": "B"
        },
        {
            "type": "Scratch",
            "defect_item": 2,
            "length": 1.91565,
            "width": 0.0230527,
            "area_mm": 0.0667888,
            "area_pixel": 344,
            "contrast": 20,
            "location": [
                "9955.56,1371.18",
                "10067.8,1450.5",
                "10070.7,1446.41",
                "9958.44,1367.09"
            ],
            "class": "defect",
            "surface": "B"
        },
        {
            "type": "Scratch",
            "defect_item": 2,
            "length": 3.62689,
            "width": 0.0252848,
            "area_mm": 0.139014,
            "area_pixel": 716,
            "contrast": 19,
            "location": [
                "10080.9,1719.81",
                "10129.2,1464.03",
                "10119.8,1462.26",
                "10071.5,1718.03"
            ],
            "class": "defect",
            "surface": "B"
        },
        {
            "type": "Scratch",
            "defect_item": 2,
            "length": 1.44096,
            "width": 0.083656,
            "area_mm": 0.119599,
            "area_pixel": 616,
            "contrast": 30,
            "location": [
                "5466.52,1593.42",
                "5565.37,1563.04",
                "5557.74,1538.21",
                "5458.89,1568.58"
            ],
            "class": "defect",
            "surface": "B"
        },
        {
            "type": "Scratch",
            "defect_item": 2,
            "length": 1.04964,
            "width": 0.0165849,
            "area_mm": 0.029123,
            "area_pixel": 150,
            "contrast": 17,
            "location": [
                "9195.52,1661.99",
                "9220.61,1733.02",
                "9224.11,1731.79",
                "9199.01,1660.76"
            ],
            "class": "defect",
            "surface": "B"
        },
        {
            "type": "Scratch",
            "defect_item": 2,
            "length": 1.14527,
            "width": 0.0386508,
            "area_mm": 0.0580519,
            "area_pixel": 299,
            "contrast": 27,
            "location": [
                "11640.2,1865.17",
                "11669.9,1788.53",
                "11661.1,1785.13",
                "11631.4,1861.77"
            ],
            "class": "defect",
            "surface": "B"
        },
        {
            "type": "Scratch",
            "defect_item": 2,
            "length": 1.26011,
            "width": 0.0289713,
            "area_mm": 0.051839,
            "area_pixel": 267,
            "contrast": 17,
            "location": [
                "1158.92,2522.17",
                "1173.92,2432.98",
                "1168.89,2432.14",
                "1153.9,2521.32"
            ],
            "class": "defect",
            "surface": "B"
        },
        {
            "type": "Scratch",
            "defect_item": 2,
            "length": 1.72843,
            "width": 0.0321546,
            "area_mm": 0.0792147,
            "area_pixel": 408,
            "contrast": 26,
            "location": [
                "11622.9,2950.92",
                "11676.3,3062.87",
                "11681.6,3060.37",
                "11628.1,2948.42"
            ],
            "class": "defect",
            "surface": "B"
        },
        {
            "type": "Scratch",
            "defect_item": 2,
            "length": 1.10074,
            "width": 0.0193039,
            "area_mm": 0.0322295,
            "area_pixel": 166,
            "contrast": 19,
            "location": [
                "9303.95,3214.95",
                "9334.95,3142.29",
                "9331.47,3140.8",
                "9300.47,3213.47"
            ],
            "class": "defect",
            "surface": "B"
        },
        {
            "type": "Scratch",
            "defect_item": 2,
            "length": 1.37939,
            "width": 0.0705361,
            "area_mm": 0.0782439,
            "area_pixel": 403,
            "contrast": 23,
            "location": [
                "7100.02,3971.85",
                "7164.81,4046.69",
                "7193.09,4022.21",
                "7128.3,3947.36"
            ],
            "class": "defect",
            "surface": "B"
        },
        {
            "type": "Scratch",
            "defect_item": 2,
            "length": 2.00002,
            "width": 0.0172579,
            "area_mm": 0.0574695,
            "area_pixel": 296,
            "contrast": 18,
            "location": [
                "7213.74,5081.04",
                "7254.66,5218.62",
                "7268.44,5214.52",
                "7227.52,5076.94"
            ],
            "class": "defect",
            "surface": "B"
        },
        {
            "type": "Scratch",
            "defect_item": 2,
            "length": 1.33248,
            "width": 0.057866,
            "area_mm": 0.0959119,
            "area_pixel": 494,
            "contrast": 40,
            "location": [
                "5135.46,5271.53",
                "5226.96,5243.74",
                "5224.13,5234.41",
                "5132.63,5262.2"
            ],
            "class": "defect",
            "surface": "B"
        },
        {
            "type": "Nick",
            "defect_item": 2,
            "length": 1.23488,
            "width": 0.306557,
            "area_mm": 0.360931,
            "area_pixel": 1859,
            "contrast": 29,
            "location": [
                "10724.5,4449.12",
                "10735.2,4537.11",
                "10778.7,4531.85",
                "10768.1,4443.86"
            ],
            "class": "defect",
            "surface": "B"
        },
        {
            "type": "Scratch",
            "defect_item": 1,
            "length": 3.14367,
            "width": 0.0650843,
            "area_mm": 0.228519,
            "area_pixel": 1177,
            "contrast": 4,
            "location": [
                "8117.64,6191.57",
                "8322.94,6285.11",
                "8330.56,6268.39",
                "8125.26,6174.84"
            ],
            "class": "defect",
            "surface": "AA"
        }
    ]
}