{
    "imei": "356715087400159",
    "model": "APL8P",
    "color": "GRAY",
    "vzw": "B",
    "defects": [
        {
            "type": "Scratch",
            "defect_item": 2,
            "length": 1.07986,
            "width": 0.0401689,
            "area_mm": 0.0561104,
            "area_pixel": 289,
            "contrast": 24,
            "location": [
                "10422.6,2235.41",
                "10457.9,2166.41",
                "10447.4,2161.08",
                "10412.2,2230.08"
            ],
            "class": "defect",
            "surface": "B"
        },
        {
            "type": "Scratch",
            "defect_item": 2,
            "length": 1.46525,
            "width": 0.201536,
            "area_mm": 0.307151,
            "area_pixel": 1582,
            "contrast": 50,
            "location": [
                "1588.82,6310.31",
                "1684.02,6265.66",
                "1672.83,6241.8",
                "1577.63,6286.46"
            ],
            "class": "defect",
            "surface": "B"
        },
        {
            "type": "Scratch",
            "defect_item": 1,
            "length": 1.43463,
            "width": 0.0790822,
            "area_mm": 0.101348,
            "area_pixel": 522,
            "contrast": 3,
            "location": [
                "5510.41,6354.06",
                "5525.65,6252.24",
                "5501.92,6248.69",
                "5486.68,6350.51"
            ],
            "class": "defect",
            "surface": "AA"
        }
    ]
}