{
    "imei": "356705082630660",
    "model": "APL8",
    "color": "GOLD",
    "vzw": "B",
    "defects": [
        {
            "type": "Scratch",
            "defect_item": 1,
            "length": 0.713565,
            "width": 0.137206,
            "area_mm": 0.0896989,
            "area_pixel": 462,
            "contrast": 20,
            "location": [
                "2005.82,1792.14",
                "2050.65,1767.38",
                "2040.25,1748.56",
                "1995.42,1773.32"
            ],
            "class": "defect",
            "surface": "B"
        },
        {
            "type": "Scratch",
            "defect_item": 1,
            "length": 0.753816,
            "width": 0.104422,
            "area_mm": 0.0862042,
            "area_pixel": 444,
            "contrast": 40,
            "location": [
                "5964.95,1856.14",
                "6012.35,1882.22",
                "6023.75,1861.5",
                "5976.35,1835.42"
            ],
            "class": "defect",
            "surface": "B"
        },
        {
            "type": "Scratch",
            "defect_item": 1,
            "length": 0.760229,
            "width": 0.127546,
            "area_mm": 0.0900873,
            "area_pixel": 464,
            "contrast": 27,
            "location": [
                "1185.34,1993.74",
                "1206.77,2043.91",
                "1232.01,2033.13",
                "1210.58,1982.96"
            ],
            "class": "defect",
            "surface": "B"
        },
        {
            "type": "Scratch",
            "defect_item": 1,
            "length": 0.814923,
            "width": 0.105073,
            "area_mm": 0.0957177,
            "area_pixel": 493,
            "contrast": 54,
            "location": [
                "6964.31,4436.16",
                "6975.62,4378.78",
                "6961.1,4375.92",
                "6949.79,4433.3"
            ],
            "class": "defect",
            "surface": "B"
        },
        {
            "type": "Scratch",
            "defect_item": 1,
            "length": 0.75898,
            "width": 0.1201,
            "area_mm": 0.0863983,
            "area_pixel": 445,
            "contrast": 54,
            "location": [
                "2214.12,4498.29",
                "2218.48,4552.59",
                "2243.2,4550.6",
                "2238.84,4496.31"
            ],
            "class": "defect",
            "surface": "B"
        },
        {
            "type": "Scratch",
            "defect_item": 1,
            "length": 0.552888,
            "width": 0.101863,
            "area_mm": 0.0287347,
            "area_pixel": 148,
            "contrast": 24,
            "location": [
                "2212.35,4623.98",
                "2251.32,4631.44",
                "2255.12,4611.58",
                "2216.15,4604.11"
            ],
            "class": "defect",
            "surface": "B"
        },
        {
            "type": "Scratch",
            "defect_item": 1,
            "length": 0.601802,
            "width": 0.11125,
            "area_mm": 0.0679537,
            "area_pixel": 350,
            "contrast": 19,
            "location": [
                "6802.38,5953.53",
                "6806.62,5910.54",
                "6789.58,5908.86",
                "6785.34,5951.85"
            ],
            "class": "defect",
            "surface": "B"
        },
        {
            "type": "Scratch",
            "defect_item": "1,2",
            "length": 1.20319,
            "width": 0.128909,
            "area_mm": 0.139791,
            "area_pixel": 720,
            "contrast": 33,
            "location": [
                "3845.87,1853.47",
                "3883.97,1930.96",
                "3903.29,1921.47",
                "3865.19,1843.98"
            ],
            "class": "defect",
            "surface": "B"
        },
        {
            "type": "Scratch",
            "defect_item": 2,
            "length": 1.01785,
            "width": 0.0351184,
            "area_mm": 0.0500916,
            "area_pixel": 258,
            "contrast": 31,
            "location": [
                "3282.95,2606.11",
                "3316.87,2541.42",
                "3301.09,2533.14",
                "3267.17,2597.84"
            ],
            "class": "defect",
            "surface": "B"
        },
        {
            "type": "Scratch",
            "defect_item": "1,2",
            "length": 1.25413,
            "width": 0.108215,
            "area_mm": 0.152993,
            "area_pixel": 788,
            "contrast": 64,
            "location": [
                "9989.47,5690.55",
                "9990.32,5600.55",
                "9973.12,5600.39",
                "9972.27,5690.39"
            ],
            "class": "defect",
            "surface": "B"
        },
        {
            "type": "Scratch",
            "defect_item": 2,
            "length": 1.03289,
            "width": 0.0512822,
            "area_mm": 0.0636824,
            "area_pixel": 328,
            "contrast": 46,
            "location": [
                "8818.07,5822",
                "8881.04,5861.1",
                "8888.26,5849.48",
                "8825.28,5810.38"
            ],
            "class": "defect",
            "surface": "B"
        },
        {
            "type": "Nick",
            "defect_item": 1,
            "length": 0.97084,
            "width": 0.309954,
            "area_mm": 0.29246,
            "area_pixel": 128,
            "contrast": 53,
            "location": [
                "6608.85,542.37",
                "6627.9,549.411",
                "6632.1,538.049",
                "6613.05,531.008"
            ],
            "class": "defect",
            "surface": "B"
        },
        {
            "type": "Discoloration",
            "region": "Switch",
            "value": 22.3003,
            "class": "measurement",
            "surface": "B"
        },
        {
            "type": "Scratch",
            "defect_item": 1,
            "length": 22.2266,
            "width": 0.0776374,
            "area_mm": 1.833,
            "area_pixel": 9441,
            "contrast": 4,
            "location": [
                "1973.87,2193.6",
                "2132.16,3780.87",
                "2184.35,3775.67",
                "2026.06,2188.4"
            ],
            "class": "defect",
            "surface": "AA"
        },
        {
            "type": "Scratch",
            "defect_item": 1,
            "length": 18.6062,
            "width": 0.0895586,
            "area_mm": 1.60313,
            "area_pixel": 8257,
            "contrast": 4,
            "location": [
                "7202.47,3337.23",
                "7945.72,4446.58",
                "7995.87,4412.98",
                "7252.62,3303.63"
            ],
            "class": "defect",
            "surface": "AA"
        },
        {
            "type": "Scratch",
            "defect_item": 1,
            "length": 1.85321,
            "width": 0.0901479,
            "area_mm": 0.161536,
            "area_pixel": 832,
            "contrast": 3,
            "location": [
                "3206.28,1570.27",
                "3277.95,1682.3",
                "3301.95,1666.95",
                "3230.28,1554.91"
            ],
            "class": "defect",
            "surface": "AA"
        },
        {
            "type": "Scratch",
            "defect_item": 1,
            "length": 2.01405,
            "width": 0.0735001,
            "area_mm": 0.140761,
            "area_pixel": 725,
            "contrast": 2,
            "location": [
                "1922.12,1652.74",
                "1947.03,1795.13",
                "1972.64,1790.65",
                "1947.73,1648.26"
            ],
            "class": "defect",
            "surface": "AA"
        },
        {
            "type": "Scratch",
            "defect_item": 1,
            "length": 4.1762,
            "width": 0.0911516,
            "area_mm": 0.399374,
            "area_pixel": 2057,
            "contrast": 3,
            "location": [
                "6188.12,1695.41",
                "6218.78,1993.55",
                "6239.32,1991.44",
                "6208.66,1693.3"
            ],
            "class": "defect",
            "surface": "AA"
        },
        {
            "type": "Scratch",
            "defect_item": 1,
            "length": 1.88636,
            "width": 0.0859222,
            "area_mm": 0.173379,
            "area_pixel": 893,
            "contrast": 3,
            "location": [
                "8296.46,2299.04",
                "8335.15,2169.31",
                "8315.55,2163.47",
                "8276.86,2293.2"
            ],
            "class": "defect",
            "surface": "AA"
        },
        {
            "type": "Scratch",
            "defect_item": 1,
            "length": 3.57667,
            "width": 0.0938988,
            "area_mm": 0.31414,
            "area_pixel": 1618,
            "contrast": 3,
            "location": [
                "6350.64,3150.29",
                "6512.47,2951.04",
                "6469.12,2915.83",
                "6307.29,3115.08"
            ],
            "class": "defect",
            "surface": "AA"
        },
        {
            "type": "Scratch",
            "defect_item": 1,
            "length": 5.70405,
            "width": 0.0919206,
            "area_mm": 0.541106,
            "area_pixel": 2787,
            "contrast": 5,
            "location": [
                "6326.19,4910.2",
                "6390.59,4505.93",
                "6353.31,4499.99",
                "6288.91,4904.26"
            ],
            "class": "defect",
            "surface": "AA"
        },
        {
            "type": "Scratch",
            "defect_item": 2,
            "length": 0.705377,
            "width": 0.134901,
            "area_mm": 0.0994066,
            "area_pixel": 512,
            "contrast": 73,
            "location": [
                "1071.39,4291.11",
                "1119.81,4276.35",
                "1111.36,4248.61",
                "1062.93,4263.38"
            ],
            "class": "defect",
            "surface": "A"
        }
    ]
}