<?xml version="1.0" encoding="utf-8" ?>
<defect_record version="1.1">
<index>9285</index>
<model>Iphone6 Gray</model>
<time>2019/06/20 11:42:00</time>
<station name="BACK">
<surface name="B">
<sensor name="smooth_surface_sensor_4" type="smooth_surface_sensor">
<parameter>
<defect_item index="1">
<enabled>1</enabled>
<color>2</color>
<threshold>25</threshold>
<defect_finder>
<sort><type>-1</type>
<general><enabled>1</enabled>
<sort>2</sort>
</general>
<scratch><enabled>1</enabled>
<sort>1</sort>
<aspect_ratio>5</aspect_ratio>
</scratch><crack><enabled>0</enabled>
<sort>3</sort>
<aspect_ratio>10</aspect_ratio>
<max_gap>40</max_gap>
</crack></sort><defect_unit>0</defect_unit>
<defect>
<item>
<length_defect>
<min_length>0.5</min_length>
<min_width>0.2</min_width>
<min_count>1</min_count>
</length_defect>
</item>
</defect>
<scratch_linking>
<enabled>1</enabled>
<major_offset>1</major_offset>
<minor_offset>0.1</minor_offset>
<angle>30</angle>
</scratch_linking>
<cluster>
<enabled>1</enabled>
<range>2</range>
<min_length>0</min_length>
<max_length>1</max_length>
<min_width>0</min_width>
<max_width>0.7</max_width>
<min_count>3</min_count>
</cluster>
</defect_finder>
</defect_item>
<defect_item index="2">
<enabled>1</enabled>
<color>0</color>
<threshold>20</threshold>
<defect_finder>
<sort><type>-1</type>
<general><enabled>1</enabled>
<sort>2</sort>
</general>
<scratch><enabled>0</enabled>
<sort>1</sort>
<aspect_ratio>5</aspect_ratio>
</scratch><crack><enabled>0</enabled>
<sort>3</sort>
<aspect_ratio>10</aspect_ratio>
<max_gap>40</max_gap>
</crack></sort><defect_unit>0</defect_unit>
<defect>
<item>
<length_defect>
<min_length>1</min_length>
<min_width>0</min_width>
<min_count>1</min_count>
</length_defect>
</item>
</defect>
<scratch_linking>
<enabled>1</enabled>
<major_offset>1.5</major_offset>
<minor_offset>0.1</minor_offset>
<angle>30</angle>
</scratch_linking>
<cluster>
<enabled>0</enabled>
<range>1</range>
<min_length>0</min_length>
<max_length>1</max_length>
<min_width>0</min_width>
<max_width>0.2</max_width>
<min_count>3</min_count>
</cluster>
</defect_finder>
</defect_item>
</parameter>
<region>795,1334,1533,5341</region>
<defect>
<item class="defect">
<type>Nick</type>
<defect_item>2</defect_item>
<length>1.6455</length>
<width>0.157264</width>
<area_mm>0.245022</area_mm>
<area_pixel>1262</area_pixel>
<contrast>49</contrast>
<location>
<point>888.581,2962.14</point>
<point>1006.67,2960.97</point>
<point>1006.37,2930.99</point>
<point>888.283,2932.16</point>
</location>
</item>
<item class="defect">
<type>Nick</type>
<defect_item>2</defect_item>
<length>1.08897</length>
<width>0.106512</width>
<area_mm>0.107173</area_mm>
<area_pixel>552</area_pixel>
<contrast>36</contrast>
<location>
<point>1006.87,2954.88</point>
<point>1084.93,2958.7</point>
<point>1086.07,2935.39</point>
<point>1008.01,2931.57</point>
</location>
</item>
<item class="defect">
<type>Nick</type>
<defect_item>2</defect_item>
<length>1.03247</length>
<width>0.0925486</width>
<area_mm>0.102707</area_mm>
<area_pixel>529</area_pixel>
<contrast>46</contrast>
<location>
<point>891.228,3331.48</point>
<point>965.305,3333.23</point>
<point>965.723,3315.58</point>
<point>891.646,3313.83</point>
</location>
</item>
</defect>
</sensor>
<sensor name="measure_table_sensor_1" type="measure_table_sensor">
<region>0,0,0,0</region>
<defect>
<item class="measurement">
<type>Discoloration</type>
<region>Rear_Cam</region>
<value>24.4041</value>
</item>
</defect>
</sensor>
</surface>
</station>
<station name="DOWN">
<surface name="B">
<sensor name="edge_sensor_1" type="edge_sensor">
<parameter>
<defect_item index="1">
<enabled>1</enabled>
<threshold>18</threshold>
<defect_finder>
<sort><type>-1</type>
<general><enabled>1</enabled>
<sort>2</sort>
</general>
<scratch><enabled>1</enabled>
<sort>1</sort>
<aspect_ratio>5</aspect_ratio>
</scratch><crack><enabled>0</enabled>
<sort>3</sort>
<aspect_ratio>10</aspect_ratio>
<max_gap>40</max_gap>
</crack></sort><defect_unit>0</defect_unit>
<defect>
<item>
<length_defect>
<min_length>0.2</min_length>
<min_width>0.2</min_width>
<min_count>1</min_count>
</length_defect>
</item>
</defect>
<scratch_linking>
<enabled>1</enabled>
<major_offset>1</major_offset>
<minor_offset>0.1</minor_offset>
<angle>30</angle>
</scratch_linking>
<cluster>
<enabled>1</enabled>
<range>2</range>
<min_length>0</min_length>
<max_length>1</max_length>
<min_width>0</min_width>
<max_width>0.7</max_width>
<min_count>3</min_count>
</cluster>
</defect_finder>
</defect_item>
<defect_item index="2">
<enabled>1</enabled>
<threshold>30</threshold>
<defect_finder>
<sort><type>-1</type>
<general><enabled>1</enabled>
<sort>2</sort>
</general>
<scratch><enabled>1</enabled>
<sort>1</sort>
<aspect_ratio>5</aspect_ratio>
</scratch><crack><enabled>0</enabled>
<sort>3</sort>
<aspect_ratio>10</aspect_ratio>
<max_gap>40</max_gap>
</crack></sort><defect_unit>0</defect_unit>
<defect>
<item>
<length_defect>
<min_length>0.5</min_length>
<min_width>0.2</min_width>
<min_count>1</min_count>
</length_defect>
</item>
</defect>
<scratch_linking>
<enabled>1</enabled>
<major_offset>1</major_offset>
<minor_offset>0.1</minor_offset>
<angle>30</angle>
</scratch_linking>
<cluster>
<enabled>0</enabled>
<range>1</range>
<min_length>0</min_length>
<max_length>1</max_length>
<min_width>0</min_width>
<max_width>0.2</max_width>
<min_count>3</min_count>
</cluster>
</defect_finder>
</defect_item>
</parameter>
<region>300,592,1567,698</region>
<defect>
<item class="defect">
<type>Scratch</type>
<defect_item>1</defect_item>
<length>3.25526</length>
<width>0.273941</width>
<area_mm>0.788725</area_mm>
<area_pixel>343</area_pixel>
<contrast>31</contrast>
<location>
<point>608.014,638.731</point>
<point>670.882,664.343</point>
<point>680.02,641.912</point>
<point>617.153,616.3</point>
</location>
</item>
</defect>
</sensor>
</surface>
</station>
<station name="UP">
<surface name="B">
<sensor name="edge_sensor_1" type="edge_sensor">
<parameter>
<defect_item index="1">
<enabled>1</enabled>
<threshold>18</threshold>
<defect_finder>
<sort><type>-1</type>
<general><enabled>1</enabled>
<sort>2</sort>
</general>
<scratch><enabled>1</enabled>
<sort>1</sort>
<aspect_ratio>5</aspect_ratio>
</scratch><crack><enabled>0</enabled>
<sort>3</sort>
<aspect_ratio>10</aspect_ratio>
<max_gap>40</max_gap>
</crack></sort><defect_unit>0</defect_unit>
<defect>
<item>
<length_defect>
<min_length>0.6</min_length>
<min_width>0.1</min_width>
<min_count>1</min_count>
</length_defect>
</item>
</defect>
<scratch_linking>
<enabled>1</enabled>
<major_offset>1</major_offset>
<minor_offset>0.1</minor_offset>
<angle>30</angle>
</scratch_linking>
<cluster>
<enabled>1</enabled>
<range>2</range>
<min_length>0</min_length>
<max_length>1</max_length>
<min_width>0</min_width>
<max_width>0.7</max_width>
<min_count>3</min_count>
</cluster>
</defect_finder>
</defect_item>
<defect_item index="2">
<enabled>0</enabled>
<threshold>15</threshold>
<defect_finder>
<sort><type>-1</type>
<general><enabled>1</enabled>
<sort>2</sort>
</general>
<scratch><enabled>1</enabled>
<sort>1</sort>
<aspect_ratio>5</aspect_ratio>
</scratch><crack><enabled>0</enabled>
<sort>3</sort>
<aspect_ratio>10</aspect_ratio>
<max_gap>40</max_gap>
</crack></sort><defect_unit>0</defect_unit>
<defect>
<item>
<length_defect>
<min_length>0.6</min_length>
<min_width>0.2</min_width>
<min_count>1</min_count>
</length_defect>
</item>
</defect>
<scratch_linking>
<enabled>1</enabled>
<major_offset>1</major_offset>
<minor_offset>0.1</minor_offset>
<angle>30</angle>
</scratch_linking>
<cluster>
<enabled>0</enabled>
<range>1</range>
<min_length>0</min_length>
<max_length>1</max_length>
<min_width>0</min_width>
<max_width>0.7</max_width>
<min_count>3</min_count>
</cluster>
</defect_finder>
</defect_item>
</parameter>
<region>359,590,1627,690</region>
<defect>
<item class="defect">
<type>Scratch</type>
<defect_item>1</defect_item>
<length>1.14347</length>
<width>0.160659</width>
<area_mm>0.170162</area_mm>
<area_pixel>74</area_pixel>
<contrast>26</contrast>
<location>
<point>1558.37,602.625</point>
<point>1580.4,611.746</point>
<point>1584.22,602.519</point>
<point>1562.19,593.399</point>
</location>
</item>
<item class="defect">
<type>Scratch</type>
<defect_item>1</defect_item>
<length>0.777864</length>
<width>0.108309</width>
<area_mm>0.105777</area_mm>
<area_pixel>46</area_pixel>
<contrast>25</contrast>
<location>
<point>1431.06,604.63</point>
<point>1446.2,610.472</point>
<point>1448.32,604.973</point>
<point>1433.19,599.132</point>
</location>
</item>
<item class="defect">
<type>Scratch</type>
<defect_item>1</defect_item>
<length>1.52127</length>
<width>0.290032</width>
<area_mm>0.466797</area_mm>
<area_pixel>203</area_pixel>
<contrast>43</contrast>
<location>
<point>1179.27,605.477</point>
<point>1189.77,635.415</point>
<point>1201.36,631.354</point>
<point>1190.86,601.416</point>
</location>
</item>
<item class="defect">
<type>Scratch</type>
<defect_item>1</defect_item>
<length>0.765289</length>
<width>0.11183</width>
<area_mm>0.0781827</area_mm>
<area_pixel>34</area_pixel>
<contrast>27</contrast>
<location>
<point>1623.22,638.606</point>
<point>1623.74,622.655</point>
<point>1618.52,622.484</point>
<point>1617.99,638.434</point>
</location>
</item>
<item class="defect">
<type>Nick</type>
<defect_item>1</defect_item>
<length>1.31383</length>
<width>0.305346</width>
<area_mm>0.411609</area_mm>
<area_pixel>179</area_pixel>
<contrast>37</contrast>
<location>
<point>1293.7,627.961</point>
<point>1295.9,600.652</point>
<point>1283.98,599.69</point>
<point>1281.77,626.999</point>
</location>
</item>
<item class="defect">
<type>PinDotGroup</type>
<defect_item>1</defect_item>
<length>4.68646</length>
<width>2.11423</width>
<area_mm>1.06466</area_mm>
<area_pixel>463</area_pixel>
<contrast>29</contrast>
<location>
<point>1478.21,623.308</point>
<point>1566.91,664.334</point>
<point>1585.42,624.318</point>
<point>1496.71,583.292</point>
</location>
</item>
</defect>
</sensor>
</surface>
</station>
<station name="LEFT">
<surface name="B">
<sensor name="edge_sensor_4" type="edge_sensor">
<parameter>
<defect_item index="1">
<enabled>1</enabled>
<threshold>20</threshold>
<defect_finder>
<sort><type>-1</type>
<general><enabled>1</enabled>
<sort>2</sort>
</general>
<scratch><enabled>1</enabled>
<sort>1</sort>
<aspect_ratio>5</aspect_ratio>
</scratch><crack><enabled>0</enabled>
<sort>3</sort>
<aspect_ratio>10</aspect_ratio>
<max_gap>40</max_gap>
</crack></sort><defect_unit>0</defect_unit>
<defect>
<item>
<length_defect>
<min_length>0.5</min_length>
<min_width>0.2</min_width>
<min_count>1</min_count>
</length_defect>
</item>
</defect>
<scratch_linking>
<enabled>1</enabled>
<major_offset>1</major_offset>
<minor_offset>0.1</minor_offset>
<angle>30</angle>
</scratch_linking>
<cluster>
<enabled>1</enabled>
<range>2</range>
<min_length>0</min_length>
<max_length>1</max_length>
<min_width>0</min_width>
<max_width>0.7</max_width>
<min_count>3</min_count>
</cluster>
</defect_finder>
</defect_item>
</parameter>
<region>974,529,1145,629</region>
<defect>
<item class="defect">
<type>Scratch</type>
<defect_item>1</defect_item>
<length>2.68405</length>
<width>0.284573</width>
<area_mm>0.701446</area_mm>
<area_pixel>307</area_pixel>
<contrast>38</contrast>
<location>
<point>1016.54,549.453</point>
<point>1072.69,548.452</point>
<point>1072.4,532.619</point>
<point>1016.26,533.62</point>
</location>
</item>
<item class="defect">
<type>Scratch</type>
<defect_item>1</defect_item>
<length>1.49042</length>
<width>0.220568</width>
<area_mm>0.290175</area_mm>
<area_pixel>127</area_pixel>
<contrast>28</contrast>
<location>
<point>1014.71,582.633</point>
<point>1045.84,580.84</point>
<point>1045.15,568.878</point>
<point>1014.02,570.671</point>
</location>
</item>
</defect>
</sensor>
</surface>
</station>
<station name="RIGHT">
<surface name="B">
<sensor name="edge_sensor_4" type="edge_sensor">
<parameter>
<defect_item index="1">
<enabled>1</enabled>
<threshold>20</threshold>
<defect_finder>
<sort><type>-1</type>
<general><enabled>1</enabled>
<sort>2</sort>
</general>
<scratch><enabled>1</enabled>
<sort>1</sort>
<aspect_ratio>5</aspect_ratio>
</scratch><crack><enabled>0</enabled>
<sort>3</sort>
<aspect_ratio>10</aspect_ratio>
<max_gap>40</max_gap>
</crack></sort><defect_unit>0</defect_unit>
<defect>
<item>
<length_defect>
<min_length>0.5</min_length>
<min_width>0.2</min_width>
<min_count>1</min_count>
</length_defect>
</item>
</defect>
<scratch_linking>
<enabled>1</enabled>
<major_offset>1</major_offset>
<minor_offset>0.1</minor_offset>
<angle>30</angle>
</scratch_linking>
<cluster>
<enabled>1</enabled>
<range>2</range>
<min_length>0</min_length>
<max_length>1</max_length>
<min_width>0</min_width>
<max_width>0.7</max_width>
<min_count>3</min_count>
</cluster>
</defect_finder>
</defect_item>
</parameter>
<region>6563,556,6748,652</region>
<defect>
<item class="defect">
<type>PinDotGroup</type>
<defect_item>1</defect_item>
<length>2.98232</length>
<width>0.900567</width>
<area_mm>0.472962</area_mm>
<area_pixel>207</area_pixel>
<contrast>38</contrast>
<location>
<point>6623.76,614.142</point>
<point>6684,597.881</point>
<point>6679.08,579.691</point>
<point>6618.85,595.952</point>
</location>
</item>
</defect>
</sensor>
<sensor name="measure_table_sensor_1" type="measure_table_sensor">
<region>0,0,0,0</region>
<defect>
<item class="measurement">
<type>Discoloration</type>
<region>Switch</region>
<value>20.3887</value>
</item>
</defect>
</sensor>
</surface>
</station>
<station name="TOP">
<surface name="AA">
<sensor name="smooth_surface_sensor_1" type="glass_sensor">
<parameter>
<defect_item index="1">
<enabled>1</enabled>
<color>0</color>
<threshold>2</threshold>
<defect_finder>
<sort><type>-1</type>
<general><enabled>1</enabled>
<sort>2</sort>
</general>
<scratch><enabled>1</enabled>
<sort>1</sort>
<aspect_ratio>5</aspect_ratio>
</scratch><crack><enabled>0</enabled>
<sort>3</sort>
<aspect_ratio>10</aspect_ratio>
<max_gap>40</max_gap>
</crack></sort><defect_unit>0</defect_unit>
<defect>
<item>
<length_defect>
<min_length>1.5</min_length>
<min_width>0</min_width>
<max_width>0.17</max_width>
<min_count>1</min_count>
</length_defect>
</item>
</defect>
<scratch_linking>
<enabled>1</enabled>
<major_offset>1.5</major_offset>
<minor_offset>0.1</minor_offset>
<angle>30</angle>
</scratch_linking>
<cluster>
<enabled>0</enabled>
<range>1</range>
<min_length>0</min_length>
<max_length>1</max_length>
<min_width>0</min_width>
<max_width>0.2</max_width>
<min_count>3</min_count>
</cluster>
</defect_finder>
</defect_item>
<defect_item index="2">
<enabled>0</enabled>
<color>0</color>
<threshold>10</threshold>
<defect_finder>
<sort><type>-1</type>
<general><enabled>1</enabled>
<sort>2</sort>
</general>
<scratch><enabled>1</enabled>
<sort>1</sort>
<aspect_ratio>5</aspect_ratio>
</scratch><crack><enabled>0</enabled>
<sort>3</sort>
<aspect_ratio>10</aspect_ratio>
<max_gap>40</max_gap>
</crack></sort><defect_unit>0</defect_unit>
<defect>
<item>
<length_defect>
<min_length>0.5</min_length>
<min_width>0.201</min_width>
<min_count>1</min_count>
</length_defect>
</item>
</defect>
<scratch_linking>
<enabled>1</enabled>
<major_offset>1</major_offset>
<minor_offset>0.1</minor_offset>
<angle>30</angle>
</scratch_linking>
<cluster>
<enabled>0</enabled>
<range>1</range>
<min_length>0</min_length>
<max_length>1</max_length>
<min_width>0</min_width>
<max_width>0.2</max_width>
<min_count>3</min_count>
</cluster>
</defect_finder>
</defect_item>
<defect_item index="3">
<enabled>1</enabled>
<color>0</color>
<threshold>50</threshold>
<defect_finder>
<sort><type>-1</type>
<general><enabled>1</enabled>
<sort>2</sort>
</general>
<scratch><enabled>1</enabled>
<sort>1</sort>
<aspect_ratio>5</aspect_ratio>
</scratch><crack><enabled>0</enabled>
<sort>3</sort>
<aspect_ratio>10</aspect_ratio>
<max_gap>40</max_gap>
</crack></sort><defect_unit>0</defect_unit>
<defect>
<item>
<length_defect>
<min_length>0.2</min_length>
<min_width>0.1</min_width>
<min_count>1</min_count>
</length_defect>
</item>
</defect>
<scratch_linking>
<enabled>1</enabled>
<major_offset>1</major_offset>
<minor_offset>0.1</minor_offset>
<angle>30</angle>
</scratch_linking>
<cluster>
<enabled>0</enabled>
<range>1</range>
<min_length>0</min_length>
<max_length>1</max_length>
<min_width>0</min_width>
<max_width>0.2</max_width>
<min_count>3</min_count>
</cluster>
</defect_finder>
</defect_item>
</parameter>
<region>1881,1537,9245,5619</region>
<defect>
<item class="defect">
<type>Scratch</type>
<defect_item>1</defect_item>
<length>2.77651</length>
<width>0.121178</width>
<area_mm>0.282882</area_mm>
<area_pixel>1457</area_pixel>
<contrast>3</contrast>
<location>
<point>8084.02,3589.99</point>
<point>8116.73,3786.54</point>
<point>8158.56,3779.58</point>
<point>8125.85,3583.02</point>
</location>
</item>
<item class="defect">
<type>Scratch</type>
<defect_item>1</defect_item>
<length>2.98292</length>
<width>0.137707</width>
<area_mm>0.395297</area_mm>
<area_pixel>2036</area_pixel>
<contrast>4</contrast>
<location>
<point>6775,4879.6</point>
<point>6809.52,5090.87</point>
<point>6842.94,5085.41</point>
<point>6808.43,4874.14</point>
</location>
</item>
<item class="defect">
<type>Nick</type>
<defect_item>3</defect_item>
<length>0.353387</length>
<width>0.155281</width>
<area_mm>0.0590227</area_mm>
<area_pixel>304</area_pixel>
<contrast>103</contrast>
<location>
<point>7322.07,5197.31</point>
<point>7346.17,5205.22</point>
<point>7351.91,5187.74</point>
<point>7327.82,5179.83</point>
</location>
</item>
</defect>
</sensor>
</surface>
<surface name="A">
<sensor name="smooth_surface_sensor_2" type="smooth_surface_sensor">
<parameter>
<defect_item index="1">
<enabled>1</enabled>
<color>0</color>
<threshold>3</threshold>
<defect_finder>
<sort><type>-1</type>
<general><enabled>1</enabled>
<sort>2</sort>
</general>
<scratch><enabled>0</enabled>
<sort>1</sort>
<aspect_ratio>5</aspect_ratio>
</scratch><crack><enabled>0</enabled>
<sort>3</sort>
<aspect_ratio>10</aspect_ratio>
<max_gap>40</max_gap>
</crack></sort><defect_unit>0</defect_unit>
<defect>
<item>
<length_defect>
<min_length>2</min_length>
<min_width>0</min_width>
<max_width>0.2</max_width>
<min_count>1</min_count>
</length_defect>
</item>
</defect>
<scratch_linking>
<enabled>1</enabled>
<major_offset>1</major_offset>
<minor_offset>0.1</minor_offset>
<angle>30</angle>
</scratch_linking>
<cluster>
<enabled>0</enabled>
<range>1</range>
<min_length>0</min_length>
<max_length>1</max_length>
<min_width>0</min_width>
<max_width>0.2</max_width>
<min_count>3</min_count>
</cluster>
</defect_finder>
</defect_item>
<defect_item index="2">
<enabled>1</enabled>
<color>0</color>
<threshold>5</threshold>
<defect_finder>
<sort><type>-1</type>
<general><enabled>1</enabled>
<sort>2</sort>
</general>
<scratch><enabled>1</enabled>
<sort>1</sort>
<aspect_ratio>5</aspect_ratio>
</scratch><crack><enabled>0</enabled>
<sort>3</sort>
<aspect_ratio>10</aspect_ratio>
<max_gap>40</max_gap>
</crack></sort><defect_unit>0</defect_unit>
<defect>
<item>
<length_defect>
<min_length>0.25</min_length>
<min_width>0.1</min_width>
<min_count>1</min_count>
</length_defect>
</item>
</defect>
<scratch_linking>
<enabled>1</enabled>
<major_offset>1</major_offset>
<minor_offset>0.1</minor_offset>
<angle>30</angle>
</scratch_linking>
<cluster>
<enabled>1</enabled>
<range>2</range>
<min_length>0</min_length>
<max_length>1</max_length>
<min_width>0</min_width>
<max_width>0.7</max_width>
<min_count>3</min_count>
</cluster>
</defect_finder>
</defect_item>
</parameter>
<region>9351,1500,10203,5666</region>
<defect>
<item class="defect">
<type>Scratch</type>
<defect_item>2</defect_item>
<length>1.2858</length>
<width>0.137616</width>
<area_mm>0.171049</area_mm>
<area_pixel>881</area_pixel>
<contrast>20</contrast>
<location>
<point>9538.09,4294.82</point>
<point>9621.52,4255.41</point>
<point>9601.99,4214.05</point>
<point>9518.55,4253.47</point>
</location>
</item>
</defect>
</sensor>
</surface>
</station>
</defect_record>
